<?xml version="1.0" encoding="ISO-8859-1" standalone="no"?><Documento><Encabezado><IdDoc><TipoDTE>33</TipoDTE><Folio>6429</Folio><FchEmis>2017-08-29</FchEmis></IdDoc><Emisor><RUTEmisor>77037960-1</RUTEmisor><RznSoc>GRUAS HORQUILLA SANTA TERESITA F.M.LTDA</RznSoc><GiroEmis>ALQUILER DE MAQUINARIAS Y EQUIPOS</GiroEmis><Acteco>712900</Acteco><Sucursal>712900</Sucursal><DirOrigen>ALFONSO DONOSO 1021</DirOrigen><CmnaOrigen>SAN BERNARDO</CmnaOrigen><CiudadOrigen>SANTIAGO</CiudadOrigen></Emisor><Receptor><RUTRecep>77079340-8</RUTRecep><RznSocRecep>2 C DISTRIBUCION LTDA</RznSocRecep><GiroRecep>PRUEBA</GiroRecep><DirRecep>SAN JOSE No.60</DirRecep><CmnaRecep>ARICA</CmnaRecep><CiudadRecep>Arica</CiudadRecep></Receptor><Totales><MntNeto>558400</MntNeto><TasaIVA>19.00</TasaIVA><IVA>106096</IVA><MntTotal>664496</MntTotal></Totales></Encabezado><Detalle><NroLinDet>1</NroLinDet><CdgItem><TpoCodigo>Interna</TpoCodigo><VlrCodigo>1</VlrCodigo></CdgItem><NmbItem>9.0 HORAS DE GRUA HORQUILLA O.T.:355</NmbItem><QtyItem>9.0</QtyItem><PrcItem>36000</PrcItem><DescuentoMonto>10000</DescuentoMonto><MontoItem>314000</MontoItem></Detalle><Detalle><NroLinDet>2</NroLinDet><CdgItem><TpoCodigo>Interna</TpoCodigo><VlrCodigo>1</VlrCodigo></CdgItem><NmbItem>1.0 HORAS DE GRUA HORQUILLA O.T.:355</NmbItem><QtyItem>1.0</QtyItem><PrcItem>50400</PrcItem><MontoItem>50400</MontoItem></Detalle><Detalle><NroLinDet>3</NroLinDet><CdgItem><TpoCodigo>Interna</TpoCodigo><VlrCodigo>2</VlrCodigo></CdgItem><NmbItem>TRASLADO GRUA A OBRA</NmbItem><QtyItem>1</QtyItem><PrcItem>50000</PrcItem><MontoItem>50000</MontoItem></Detalle><Detalle><NroLinDet>4</NroLinDet><CdgItem><TpoCodigo>Interna</TpoCodigo><VlrCodigo>1</VlrCodigo></CdgItem><NmbItem>4.0 HORAS DE GRUA HORQUILLA O.T.:356</NmbItem><QtyItem>4.0</QtyItem><PrcItem>18000</PrcItem><MontoItem>72000</MontoItem></Detalle><Detalle><NroLinDet>5</NroLinDet><CdgItem><TpoCodigo>Interna</TpoCodigo><VlrCodigo>1</VlrCodigo></CdgItem><NmbItem>4.0 HORAS DE GRUA HORQUILLA O.T.:357</NmbItem><QtyItem>4.0</QtyItem><PrcItem>18000</PrcItem><MontoItem>72000</MontoItem></Detalle><Adjuntos><Observacion>OC: 13</Observacion><Impresora>impresora</Impresora><Copias>2</Copias></Adjuntos></Documento>